{
  "posts": [
    {
      "id": 1,
      "title": "json-server",
      "author": "typicode"
    },
    {
      "id": 2,
      "title": "json-server",
      "author": "typicode"
    },
    {
      "id": 3,
      "title": "json-server",
      "author": "typicode"
    },
    {
      "id": 4,
      "title": "json-server",
      "author": "typicode"
    }
  ],
  "comments": [
    {
      "id": 1,
      "content": "some comment",
      "postId": 1
    },
    {
      "id": 2,
      "content": ""
    },
    {
      "id": 3,
      "content": ""
    },
    {
      "id": 4,
      "content": "ㅇㄹㅇㄹ"
    },
    {
      "id": 5,
      "content": "댓글 "
    }
  ],
  "profile": {
    "name": "typicode"
  }
}
